{
  "serviceResponse":{
    "userOrderParameters":{
      "userParameter":[{
        "userParameterType":{
          "$":"cpr",
          "@":"oa"
        },
        "parameterRequired":{
          "$":"1",
          "@":"oa"
        },
        "@":"oa"
      },{
        "userParameterType":{
          "$":"pincode",
          "@":"oa"
        },
        "parameterRequired":{
          "$":"1",
          "@":"oa"
        },
        "@":"oa"
      },{
        "userParameterType":{
          "$":"userName",
          "@":"oa"
        },
        "parameterRequired":{
          "$":"1",
          "@":"oa"
        },
        "@":"oa"
      },{
        "userParameterType":{
          "$":"userAddress",
          "@":"oa"
        },
        "parameterRequired":{
          "$":"1",
          "@":"oa"
        },
        "@":"oa"
      },{
        "userParameterType":{
          "$":"userMail",
          "@":"oa"
        },
        "parameterRequired":{
          "$":"0",
          "@":"oa"
        },
        "@":"oa"
      },{
        "userParameterType":{
          "$":"userTelephone",
          "@":"oa"
        },
        "parameterRequired":{
          "$":"0",
          "@":"oa"
        },
        "@":"oa"
      }],
      "userIdTxt":[{
        "$":"CPR-nummer eller 6-cifret id-nummer",
        "@language":{
          "$":"dan",
          "@":"oa"
        },
        "@":"oa"
      }],
      "orderParameters":[{
        "orderMaterialType":{
          "$":"cdrom",
          "@":"oa"
        },
        "orderType":{
          "$":"ill",
          "@":"oa"
        },
        "@":"oa"
      },{
        "orderMaterialType":{
          "$":"monograph",
          "@":"oa"
        },
        "orderType":{
          "$":"ill",
          "@":"oa"
        },
        "@":"oa"
      },{
        "orderMaterialType":{
          "$":"music",
          "@":"oa"
        },
        "orderType":{
          "$":"ill",
          "@":"oa"
        },
        "@":"oa"
      },{
        "orderMaterialType":{
          "$":"newspaper",
          "@":"oa"
        },
        "orderType":{
          "$":"local",
          "@":"oa"
        },
        "@":"oa"
      },{
        "orderMaterialType":{
          "$":"newspaper",
          "@":"oa"
        },
        "orderType":{
          "$":"ill",
          "@":"oa"
        },
        "@":"oa"
      },{
        "orderMaterialType":{
          "$":"journal",
          "@":"oa"
        },
        "orderType":{
          "$":"local",
          "@":"oa"
        },
        "itemParameter":[{
          "itemParameterType":{
            "$":"volume",
            "@":"oa"
          },
          "parameterRequired":{
            "$":"1",
            "@":"oa"
          },
          "@":"oa"
        },{
          "itemParameterType":{
            "$":"issue",
            "@":"oa"
          },
          "parameterRequired":{
            "$":"1",
            "@":"oa"
          },
          "@":"oa"
        },{
          "itemParameterType":{
            "$":"publicationDateOfComponent",
            "@":"oa"
          },
          "parameterRequired":{
            "$":"1",
            "@":"oa"
          },
          "@":"oa"
        },{
          "itemParameterType":{
            "$":"pagination",
            "@":"oa"
          },
          "parameterRequired":{
            "$":"0",
            "@":"oa"
          },
          "@":"oa"
        },{
          "itemParameterType":{
            "$":"authorOfComponent",
            "@":"oa"
          },
          "parameterRequired":{
            "$":"0",
            "@":"oa"
          },
          "@":"oa"
        },{
          "itemParameterType":{
            "$":"titleOfComponent",
            "@":"oa"
          },
          "parameterRequired":{
            "$":"0",
            "@":"oa"
          },
          "@":"oa"
        }],
        "@":"oa"
      },{
        "orderMaterialType":{
          "$":"journal",
          "@":"oa"
        },
        "orderType":{
          "$":"ill",
          "@":"oa"
        },
        "itemParameter":[{
          "itemParameterType":{
            "$":"volume",
            "@":"oa"
          },
          "parameterRequired":{
            "$":"0",
            "@":"oa"
          },
          "@":"oa"
        },{
          "itemParameterType":{
            "$":"issue",
            "@":"oa"
          },
          "parameterRequired":{
            "$":"1",
            "@":"oa"
          },
          "@":"oa"
        },{
          "itemParameterType":{
            "$":"publicationDateOfComponent",
            "@":"oa"
          },
          "parameterRequired":{
            "$":"1",
            "@":"oa"
          },
          "@":"oa"
        },{
          "itemParameterType":{
            "$":"pagination",
            "@":"oa"
          },
          "parameterRequired":{
            "$":"0",
            "@":"oa"
          },
          "@":"oa"
        },{
          "itemParameterType":{
            "$":"authorOfComponent",
            "@":"oa"
          },
          "parameterRequired":{
            "$":"0",
            "@":"oa"
          },
          "@":"oa"
        },{
          "itemParameterType":{
            "$":"titleOfComponent",
            "@":"oa"
          },
          "parameterRequired":{
            "$":"0",
            "@":"oa"
          },
          "@":"oa"
        }],
        "@":"oa"
      },{
        "orderMaterialType":{
          "$":"video",
          "@":"oa"
        },
        "orderType":{
          "$":"ill",
          "@":"oa"
        },
        "@":"oa"
      }],
      "agencyParameters":{
        "borrowerCheckParameters":[{
          "borrowerCheckSystem":{
            "$":"Filmstriben",
            "@":"oa"
          },
          "borrowerCheck":{
            "$":"0",
            "@":"oa"
          },
          "@":"oa"
        },{
          "borrowerCheckSystem":{
            "$":"SMS service",
            "@":"oa"
          },
          "borrowerCheck":{
            "$":"0",
            "@":"oa"
          },
          "@":"oa"
        },{
          "borrowerCheckSystem":{
            "$":"Test Fjernadgang 2",
            "@":"oa"
          },
          "borrowerCheck":{
            "$":"0",
            "@":"oa"
          },
          "@":"oa"
        },{
          "borrowerCheckSystem":{
            "$":"Test Fjernadgang 3",
            "@":"oa"
          },
          "borrowerCheck":{
            "$":"0",
            "@":"oa"
          },
          "@":"oa"
        },{
          "borrowerCheckSystem":{
            "$":"bibliotek.dk",
            "@":"oa"
          },
          "borrowerCheck":{
            "$":"1",
            "@":"oa"
          },
          "@":"oa"
        },{
          "borrowerCheckSystem":{
            "$":"eBib",
            "@":"oa"
          },
          "borrowerCheck":{
            "$":"0",
            "@":"oa"
          },
          "@":"oa"
        },{
          "borrowerCheckSystem":{
            "$":"netpunkt",
            "@":"oa"
          },
          "borrowerCheck":{
            "$":"0",
            "@":"oa"
          },
          "@":"oa"
        },{
          "borrowerCheckSystem":{
            "$":"proxyen.dk",
            "@":"oa"
          },
          "borrowerCheck":{
            "$":"0",
            "@":"oa"
          },
          "@":"oa"
        }],
        "acceptOrderFromUnknownUser":{
          "$":"0",
          "@":"oa"
        },
        "acceptOrderAgencyOffline":{
          "$":"1",
          "@":"oa"
        },
        "payForPostage":{
          "$":"1",
          "@":"oa"
        },
        "@":"oa"
      },
      "@":"oa"
    },
    "@":"oa"
  },
  "@namespaces":{
    "oa":"http:\/\/oss.dbc.dk\/ns\/openagency"
  }
}